biosim_client/__init__.py
biosim_client/api/__init__.py
biosim_client/api/api_specs/biosim.yaml
biosim_client/api/api_specs/simdata.json
biosim_client/api/biosim/__init__.py
biosim_client/api/biosim/api/__init__.py
biosim_client/api/biosim/api/default_api.py
biosim_client/api/biosim/api/verification_api.py
biosim_client/api/biosim/api_client.py
biosim_client/api/biosim/api_response.py
biosim_client/api/biosim/configuration.py
biosim_client/api/biosim/docs/BiosimSimulationRun.md
biosim_client/api/biosim/docs/BiosimSimulationRunStatus.md
biosim_client/api/biosim/docs/BiosimulatorVersion.md
biosim_client/api/biosim/docs/CompareSettings.md
biosim_client/api/biosim/docs/ComparisonStatistics.md
biosim_client/api/biosim/docs/DefaultApi.md
biosim_client/api/biosim/docs/GenerateStatisticsActivityOutput.md
biosim_client/api/biosim/docs/HDF5Attribute.md
biosim_client/api/biosim/docs/HDF5Dataset.md
biosim_client/api/biosim/docs/HDF5File.md
biosim_client/api/biosim/docs/HDF5Group.md
biosim_client/api/biosim/docs/HTTPValidationError.md
biosim_client/api/biosim/docs/Hdf5DataValues.md
biosim_client/api/biosim/docs/RunData.md
biosim_client/api/biosim/docs/SimulationRunInfo.md
biosim_client/api/biosim/docs/ValidationError.md
biosim_client/api/biosim/docs/ValidationErrorLocInner.md
biosim_client/api/biosim/docs/Value.md
biosim_client/api/biosim/docs/VerificationApi.md
biosim_client/api/biosim/docs/VerifyWorkflowOutput.md
biosim_client/api/biosim/docs/VerifyWorkflowStatus.md
biosim_client/api/biosim/exceptions.py
biosim_client/api/biosim/models/__init__.py
biosim_client/api/biosim/models/biosim_simulation_run.py
biosim_client/api/biosim/models/biosim_simulation_run_status.py
biosim_client/api/biosim/models/biosimulator_version.py
biosim_client/api/biosim/models/compare_settings.py
biosim_client/api/biosim/models/comparison_statistics.py
biosim_client/api/biosim/models/generate_statistics_activity_output.py
biosim_client/api/biosim/models/hdf5_attribute.py
biosim_client-0.2.4.dist-info/LICENSE
biosim_client-0.2.4.dist-info/METADATA
biosim_client-0.2.4.dist-info/WHEEL
biosim_client-0.2.4.dist-info/RECORD
