Metadata-Version: 2.1
Name: biosim_client
Version: 0.2.4
Summary: This is a library to access biosimulations.org APIs.
Home-page: https://github.com/biosimulations/biosim-client
Author: Jim Schaff
Author-email: schaff@uchc.edu
Requires-Python: >=3.10,<4.0
Classifier: Programming Language :: Python :: 3
Classifier: Programming Language :: Python :: 3.10
Classifier: Programming Language :: Python :: 3.11
Classifier: Programming Language :: Python :: 3.12
Requires-Dist: ipython (>=8.32.0,<9.0.0)
Requires-Dist: matplotlib (>=3.9.2,<4.0.0)
Requires-Dist: numpy (>=2.0.2,<3.0)
Requires-Dist: pandas (>=2.2.3,<3.0.0)
Requires-Dist: pillow (>=11.1.0,<12.0.0)
Requires-Dist: pydantic (>=2.9.2,<3.0.0)
Requires-Dist: pymupdf (>=1.25.3,<2.0.0)
Requires-Dist: python-dateutil (>=2.9.0.post0,<3.0.0)
Requires-Dist: typing-extensions (>=4.12.2,<5.0.0)
Requires-Dist: urllib3 (>=2.2.3,<3.0.0)
Project-URL: Documentation, https://jcschaff.github.io/biosim-client/
Project-URL: Repository, https://github.com/biosimulations/biosim-client
